{
    "name": "Angamaly Diaries",
    "Director": [
        "Lijo Jose Pellissery"
    ],
    "country": "India",
    "language": [
        "Malayalam"
    ],
    "posterUrl": "https://www.imdb.com/title/tt6167894/mediaviewer/rm806501632/?ref_=tt_ov_i",
    "bio": "Vincent Pepe who wanted to be a powerful leader of a righteous gang that ruled the city, like his seniors. And then there's the rival clan with the malicious gangsters of Angamaly a locale o... Read all",
    "runtime": "2h 12m",
    "gener": [
        "Action"
    ]
}